astro_databricks/__init__.py
astro_databricks/constants.py
astro_databricks/operators/__init__.py
astro_databricks/operators/notebook.py
astro_databricks/operators/workflow.py
astro_databricks/plugins/__init__.py
astro_databricks/plugins/plugin.py
astro_providers_databricks-0.1.0a1.dist-info/METADATA
astro_providers_databricks-0.1.0a1.dist-info/WHEEL
astro_providers_databricks-0.1.0a1.dist-info/entry_points.txt
astro_providers_databricks-0.1.0a1.dist-info/licenses/LICENSE
astro_providers_databricks-0.1.0a1.dist-info/RECORD
