Metadata-Version: 2.1
Name: astro-providers-databricks
Version: 0.1.0a1
Summary: Affordable Databricks Workflows in Apache Airflow
Project-URL: Homepage, https://github.com/astronomer/astro-providers-databricks/
Project-URL: Documentation, https://github.com/astronomer/astro-providers-databricks/
Author-email: Astronomer <humans@astronomer.io>
License-Expression: Apache-2.0
License-File: LICENSE
Keywords: airflow,apache-airflow,astronomer,dags
Classifier: Development Status :: 3 - Alpha
Classifier: Framework :: Apache Airflow
Classifier: Framework :: Apache Airflow :: Provider
Classifier: Intended Audience :: Developers
Classifier: License :: OSI Approved :: Apache Software License
Classifier: Operating System :: OS Independent
Classifier: Programming Language :: Python
Classifier: Programming Language :: Python :: 3
Classifier: Programming Language :: Python :: 3.7
Classifier: Programming Language :: Python :: 3.8
Classifier: Programming Language :: Python :: 3.9
Classifier: Programming Language :: Python :: 3.10
Requires-Python: >=3.7
Requires-Dist: apache-airflow-providers-databricks>=2.2.0
Requires-Dist: apache-airflow>=2.2.4
Requires-Dist: databricks-cli
Requires-Dist: databricks-sql-connector>=2.0.4; python_version >= '3.10'
Requires-Dist: mergedeep
Provides-Extra: docs
Requires-Dist: pydata-sphinx-theme; extra == 'docs'
Requires-Dist: sphinx; extra == 'docs'
Requires-Dist: sphinx-autobuild; extra == 'docs'
Requires-Dist: sphinx-tabs; extra == 'docs'
Provides-Extra: tests
Requires-Dist: mypy; extra == 'tests'
Requires-Dist: pytest-cov; extra == 'tests'
Requires-Dist: pytest-describe; extra == 'tests'
Requires-Dist: pytest-dotenv; extra == 'tests'
Requires-Dist: pytest-split; extra == 'tests'
Requires-Dist: pytest>=6.0; extra == 'tests'
Requires-Dist: requests-mock; extra == 'tests'
Requires-Dist: sqlalchemy-stubs; extra == 'tests'
Requires-Dist: types-requests; extra == 'tests'
